inkscape_figures_fuzzel/__init__.py
inkscape_figures_fuzzel/main.py
inkscape_figures_fuzzel/picker.py
inkscape_figures_fuzzel-1.0.7.1.dist-info/METADATA
inkscape_figures_fuzzel-1.0.7.1.dist-info/WHEEL
inkscape_figures_fuzzel-1.0.7.1.dist-info/entry_points.txt
inkscape_figures_fuzzel-1.0.7.1.dist-info/licenses/LICENSE
inkscape_figures_fuzzel-1.0.7.1.dist-info/RECORD
