Metadata-Version: 2.4
Name: inkscape-figures-fuzzel
Version: 1.0.7.1
Summary: Script for managing inkscape figures using fuzzel on Wayland
Project-URL: Repository, https://github.com/Hugelamb/inkscape-figures-fuzzel/
Author: Hugh Lam
License-File: LICENSE
Classifier: License :: OSI Approved :: MIT License
Classifier: Programming Language :: Python :: 3
Classifier: Programming Language :: Python :: 3.13
Requires-Python: >=3.7
Requires-Dist: appdirs
Requires-Dist: click
Requires-Dist: daemonize
Requires-Dist: pyperclip
